<root ddd="file:////E:/Dev_tool/unicodeTochar/eManual_Data_BUR_UNICODE_CONVERT_FINAL.py" sourcename="E:/Dev_tool/unicodeTochar/eManual_Data_BUR_UNICODE_CONVERT_FINAL.py">rules = [&#xD;
        { <List><from>u"\u1047((?=[\u1000-\u1021]\u103a)|(?=[\u102c-\u1030\u1032\u1036-\u1038\u103d\u103e]))</from>",<to>u"\u101b</to></List> }, { <List><from>u"\u1040\u102d(?!\u0020?/)</from>",<to>u"\u101d\u102d</to></List> }, { <List><from>u"\u103c</from>",<to>u"\u103d</to></List> }, { <List><from>u"(\u103d|\u1087)</from>",<to>u"\u103e</to></List> }, { <List><from>u"\u103c</from>",<to>u"\u103d</to></List> }, { <List><from>u"(\u103b|\u107e|\u107f|\u1080|\u1081|\u1082|\u1083|\u1084)</from>",<to>u"\u103c</to></List> }, { <List><from>u"(\u103a|\u107d)</from>",<to>u"\u103b</to></List> }, { <List><from>u"\u1039</from>",<to>u"\u103a</to></List> }, { <List><from>u"\u106a</from>",<to>u"\u1009</to></List> }, { <List><from>u"\u106b</from>",<to>u"\u100a</to></List> }, { <List><from>u"\u106c</from>",<to>u"\u1039\u100b</to></List> }, { <List><from>u"\u106d</from>",<to>u"\u1039\u100c</to></List> }, { <List><from>u"\u106e</from>",<to>u"\u100d\u1039\u100d</to></List> }, { <List><from>u"\u106f</from>",<to>u"\u100d\u1039\u100e</to></List> }, { <List><from>u"\u1070</from>",<to>u"\u1039\u100f</to></List> }, { <List><from>u"(\u1071|\u1072)</from>",<to>u"\u1039\u1010</to></List> }, { <List><from>u"\u1060</from>",<to>u"\u1039\u1000</to></List> }, { <List><from>u"\u1061</from>",<to>u"\u1039\u1001</to></List> }, { <List><from>u"\u1062</from>",<to>u"\u1039\u1002</to></List> }, { <List><from>u"\u1063</from>",<to>u"\u1039\u1003</to></List> }, { <List><from>u"\u1065</from>",<to>u"\u1039\u1005</to></List> }, { <List><from>u"\u1068</from>",<to>u"\u1039\u1007</to></List> }, { <List><from>u"\u1069</from>",<to>u"\u1039\u1008</to></List> }, { <List><from>u"/(\u1073|\u1074)/g</from>",<to>u"\u1039\u1011</to></List> }, { <List><from>u"\u1075</from>",<to>u"\u1039\u1012</to></List> }, { <List><from>u"\u1076</from>",<to>u"\u1039\u1013</to></List> }, { <List><from>u"\u1077</from>",<to>u"\u1039\u1014</to></List> }, { <List><from>u"\u1078</from>",<to>u"\u1039\u1015</to></List> }, { <List><from>u"\u1079</from>",<to>u"\u1039\u1016</to></List> }, { <List><from>u"\u107a</from>",<to>u"\u1039\u1017</to></List> }, { <List><from>u"\u107c</from>",<to>u"\u1039\u1019</to></List> }, { <List><from>u"\u1085</from>",<to>u"\u1039\u101c</to></List> }, { <List><from>u"\u1033</from>",<to>u"\u102f</to></List> }, { <List><from>u"\u1034</from>",<to>u"\u1030</to></List> }, { <List><from>u"\u103f</from>",<to>u"\u1030</to></List> }, { <List><from>u"\u1086</from>",<to>u"\u103f</to></List> }, { <List><from>u"\u1036\u1088</from>",<to>u"\u1088\u1036</to></List> }, { <List><from>u"\u1088</from>",<to>u"\u103e\u102f</to></List> }, { <List><from>u"\u1089</from>",<to>u"\u103e\u1030</to></List> }, { <List><from>u"\u108a</from>",<to>u"\u103d\u103e</to></List> }, { <List><from>u"([\u1000-\u1021])\u1064</from>",<to>u"\u1004\u103a\u1039\\1</to></List> }, { <List><from>u"([\u1000-\u1021])\u108b</from>",<to>u"\u1004\u103a\u1039\\1\u102d</to></List> }, { <List><from>u"([\u1000-\u1021])\u108c</from>",<to>u"\u1004\u103a\u1039\\1\u102e</to></List> }, { <List><from>u"([\u1000-\u1021])\u108d</from>",<to>u"\u1004\u103a\u1039\\1\u1036</to></List> }, { <List><from>u"\u108e</from>",<to>u"\u102d\u1036</to></List> }, { <List><from>u"\u108f</from>",<to>u"\u1014</to></List> }, { <List><from>u"\u1090</from>",<to>u"\u101b</to></List> }, { <List><from>u"\u1091</from>",<to>u"\u100f\u1039\u1091</to></List> }, { <List><from>u"\u1019\u102c(\u107b|\u1093)</from>",<to>u"\u1019\u1039\u1018\u102c</to></List> }, { <List><from>u"(\u107b|\u1093)</from>",<to>u"\u103a\u1018</to></List> }, { <List><from>u"(\u1094|\u1095)</from>",<to>u"\u1037</to></List> }, { <List><from>u"\u1096</from>",<to>u"\u1039\u1010\u103d</to></List> }, { <List><from>u"\u1097</from>",<to>u"\u100b\u1039\u100b</to></List> }, { <List><from>u"\u103c([\u1000-\u1021])([\u1000-\u1021])?</from>",<to>u"\\1\u103c\\2</to></List> }, { <List><from>u"([\u1000-\u1021])\u103c\u103a</from>",<to>u"\u103c\\1\u103a</to></List> }, { <List><from>u"\u1031([\u1000-\u1021])(\u103e)?(\u103b)?</from>",<to>u"\\1\\2\\3\u1031</to></List> }, { <List><from>u"([\u1000-\u1021])\u1031([\u103b\u103c\u103d\u103e]+)</from>",<to>u"\\1\\2\u1031</to></List> }, { <List><from>u"\u1032\u103d</from>",<to>u"\u103d\u1032</to></List> }, { <List><from>u"\u103d\u103b</from>",<to>u"\u103b\u103d</to></List> }, { <List><from>u"\u103a\u1037</from>",<to>u"\u1037\u103a</to></List> }, { <List><from>u"\u102f(\u102d|\u102e|\u1036|\u1037)\u102f</from>",<to>u"\u102f\\1</to></List> }, { <List><from>u"\u102f\u102f</from>",<to>u"\u102f</to></List> }, { <List><from>u"(\u102f|\u1030)(\u102d|\u102e)</from>",<to>u"\\2\\1</to></List> }, { <List><from>u"(\u103e)(\u103b|\u1037)</from>",<to>u"\\2\\1</to></List> }, { <List><from>u"\u1025(\u103a|\u102c)</from>",<to>u"\u1009\\1</to></List> }, { <List><from>u"\u1025\u102e</from>",<to>u"\u1026</to></List> }, { <List><from>u"\u1005\u103b</from>",<to>u"\u1008</to></List> }, { <List><from>u"\u1036(\u102f|\u1030)</from>",<to>u"\\1\u1036</to></List> }, { <List><from>u"\u1031\u1037\u103e</from>",<to>u"\u103e\u1031\u1037</to></List> }, { <List><from>u"\u1031\u103e\u102c</from>",<to>u"\u103e\u1031\u102c</to></List> }, { <List><from>u"\u105a</from>",<to>u"\u102b\u103a</to></List> }, { <List><from>u"\u1031\u103b\u103e</from>",<to>u"\u103b\u103e\u1031</to></List> }, { <List><from>u"(\u102d|\u102e)(\u103d|\u103e)</from>",<to>u"\\2\\1</to></List> }, { <List><from>u"\u102c\u1039([\u1000-\u1021])</from>",<to>u"\u1039\\1\u102c</to></List> }, { <List><from>u"\u103c\u1004\u103a\u1039([\u1000-\u1021])</from>",<to>u"\u1004\u103a\u1039\\1\u103c</to></List> }, { <List><from>u"\u1039\u103c\u103a\u1039([\u1000-\u1021])</from>",<to>u"\u103a\u1039\\1\u103c</to></List> }, { <List><from>u"\u103c\u1039([\u1000-\u1021])</from>",<to>u"\u1039\\1\u103c</to></List> }, { <List><from>u"\u1036\u1039([\u1000-\u1021])</from>",<to>u"\u1039\\1\u1036</to></List> }, { <List><from>u"\u1092</from>",<to>u"\u100b\u1039\u100c</to></List> }, { <List><from>u"\u104e</from>",<to>u"\u104e\u1004\u103a\u1038</to></List> }, { <List><from>u"\u1040(\u102b|\u102c|\u1036)</from>",<to>u"\u101d\\1</to></List> }, { <List><from>u"\u1025\u1039</from>",<to>u"\u1009\u1039</to></List> }, { <List><from>u"([\u1000-\u1021])\u103c\u1031\u103d</from>",<to>u"\\1\u103c\u103d\u1031</to></List> }, { <List><from>u"([\u1000-\u1021])\u103d\u1031\u103b</from>",<to>u"\\1\u103b\u103d\u1031</to></List> }&#xD;
    ]&#xD;
    </root>